{
    "sourceFile": "app.js",
    "activeCommit": 0,
    "commits": [
        {
            "activePatchIndex": 21,
            "patches": [
                {
                    "date": 1635949749529,
                    "content": "Index: \n===================================================================\n--- \n+++ \n"
                },
                {
                    "date": 1635949787006,
                    "content": "Index: \n===================================================================\n--- \n+++ \n@@ -40,9 +40,9 @@\n \n //Fetch Data from API\n \n async function getDummyData() {\n-  const apiUrl = \"http://dummy.restapiexample.com/api/v1/employees\"\n+  const apiUrl = \"restapi.json\"\n \n   const response = await fetch(apiUrl)\n   const barChatData = await response.json()\n   \n"
                },
                {
                    "date": 1635949797371,
                    "content": "Index: \n===================================================================\n--- \n+++ \n@@ -40,9 +40,9 @@\n \n //Fetch Data from API\n \n async function getDummyData() {\n-  const apiUrl = \"restapi.json\"\n+  const apiUrl = \"http://dummy.restapiexample.com/api/v1/employees\"\n \n   const response = await fetch(apiUrl)\n   const barChatData = await response.json()\n   \n"
                },
                {
                    "date": 1635949815954,
                    "content": "Index: \n===================================================================\n--- \n+++ \n@@ -40,9 +40,9 @@\n \n //Fetch Data from API\n \n async function getDummyData() {\n-  const apiUrl = \"http://dummy.restapiexample.com/api/v1/employees\"\n+  const apiUrl = \"restapi.json\"\n \n   const response = await fetch(apiUrl)\n   const barChatData = await response.json()\n   \n"
                },
                {
                    "date": 1635949830005,
                    "content": "Index: \n===================================================================\n--- \n+++ \n@@ -40,9 +40,9 @@\n \n //Fetch Data from API\n \n async function getDummyData() {\n-  const apiUrl = \"restapi.json\"\n+  const apiUrl = \"http://dummy.restapiexample.com/api/v1/employees\"\n \n   const response = await fetch(apiUrl)\n   const barChatData = await response.json()\n   \n"
                },
                {
                    "date": 1635950039858,
                    "content": "Index: \n===================================================================\n--- \n+++ \n@@ -40,9 +40,9 @@\n \n //Fetch Data from API\n \n async function getDummyData() {\n-  const apiUrl = \"http://dummy.restapiexample.com/api/v1/employees\"\n+  const apiUrl = \"restapi.json\";\n \n   const response = await fetch(apiUrl)\n   const barChatData = await response.json()\n   \n"
                },
                {
                    "date": 1635950054432,
                    "content": "Index: \n===================================================================\n--- \n+++ \n@@ -40,9 +40,9 @@\n \n //Fetch Data from API\n \n async function getDummyData() {\n-  const apiUrl = \"restapi.json\";\n+  const apiUrl = \"http://dummy.restapiexample.com/api/v1/employees\";\n \n   const response = await fetch(apiUrl)\n   const barChatData = await response.json()\n   \n"
                },
                {
                    "date": 1635950132859,
                    "content": "Index: \n===================================================================\n--- \n+++ \n@@ -40,9 +40,9 @@\n \n //Fetch Data from API\n \n async function getDummyData() {\n-  const apiUrl = \"http://dummy.restapiexample.com/api/v1/employees\";\n+  const apiUrl = \"https://gist.githubusercontent.com/cbmgit/852c2702d4342e7811c95f8ffc2f017f/raw/InsuranceCompanies.json\";\n \n   const response = await fetch(apiUrl)\n   const barChatData = await response.json()\n   \n"
                },
                {
                    "date": 1635950140961,
                    "content": "Index: \n===================================================================\n--- \n+++ \n@@ -40,9 +40,9 @@\n \n //Fetch Data from API\n \n async function getDummyData() {\n-  const apiUrl = \"https://gist.githubusercontent.com/cbmgit/852c2702d4342e7811c95f8ffc2f017f/raw/InsuranceCompanies.json\";\n+  const apiUrl = \"http://dummy.restapiexample.com/api/v1/employees\";\n \n   const response = await fetch(apiUrl)\n   const barChatData = await response.json()\n   \n"
                },
                {
                    "date": 1635950722898,
                    "content": "Index: \n===================================================================\n--- \n+++ \n@@ -40,9 +40,9 @@\n \n //Fetch Data from API\n \n async function getDummyData() {\n-  const apiUrl = \"http://dummy.restapiexample.com/api/v1/employees\";\n+  const apiUrl = \"https://json.extendsclass.com/bin/24cb4afca81e\";\n \n   const response = await fetch(apiUrl)\n   const barChatData = await response.json()\n   \n"
                },
                {
                    "date": 1635950733632,
                    "content": "Index: \n===================================================================\n--- \n+++ \n@@ -40,9 +40,9 @@\n \n //Fetch Data from API\n \n async function getDummyData() {\n-  const apiUrl = \"https://json.extendsclass.com/bin/24cb4afca81e\";\n+  const apiUrl = \"https://json.extendsclass.com/bin/x\";\n \n   const response = await fetch(apiUrl)\n   const barChatData = await response.json()\n   \n"
                },
                {
                    "date": 1635950739580,
                    "content": "Index: \n===================================================================\n--- \n+++ \n@@ -40,9 +40,9 @@\n \n //Fetch Data from API\n \n async function getDummyData() {\n-  const apiUrl = \"https://json.extendsclass.com/bin/x\";\n+  const apiUrl = \"https://json.extendsclass.com/bin/24cb4afca81e\";\n \n   const response = await fetch(apiUrl)\n   const barChatData = await response.json()\n   \n"
                },
                {
                    "date": 1635951687537,
                    "content": "Index: \n===================================================================\n--- \n+++ \n@@ -6,9 +6,9 @@\n const ctx = document.getElementById('myChart').getContext('2d');\n \n const chart = new Chart(ctx, {\n     // The type of chart we want to create\n-    type: 'bar',\n+    type: 'line',\n \n     // The data for our dataset\n     data: {\n         labels: employeeLabel,\n"
                },
                {
                    "date": 1635951705610,
                    "content": "Index: \n===================================================================\n--- \n+++ \n@@ -13,15 +13,15 @@\n     data: {\n         labels: employeeLabel,\n         datasets: [{\n             label: 'Employee Salary',\n-            backgroundColor: 'blue',\n+            backgroundColor: '',\n             borderColor: 'rgb(255, 99, 132)',\n             data: employeeSalaryData\n         },\n         {\n           label: 'Employee Date',\n-          backgroundColor: 'pink',\n+          backgroundColor: '',\n           borderColor: 'rgb(255, 99, 132)',\n           data: employeeDateData\n       }\n       ]\n"
                },
                {
                    "date": 1635951722849,
                    "content": "Index: \n===================================================================\n--- \n+++ \n@@ -14,9 +14,9 @@\n         labels: employeeLabel,\n         datasets: [{\n             label: 'Employee Salary',\n             backgroundColor: '',\n-            borderColor: 'rgb(255, 99, 132)',\n+            borderColor: 'black',\n             data: employeeSalaryData\n         },\n         {\n           label: 'Employee Date',\n"
                },
                {
                    "date": 1635951752393,
                    "content": "Index: \n===================================================================\n--- \n+++ \n@@ -14,15 +14,15 @@\n         labels: employeeLabel,\n         datasets: [{\n             label: 'Employee Salary',\n             backgroundColor: '',\n-            borderColor: 'black',\n+            borderColor: '#0A2558',\n             data: employeeSalaryData\n         },\n         {\n           label: 'Employee Date',\n           backgroundColor: '',\n-          borderColor: 'rgb(255, 99, 132)',\n+          borderColor: '#0A2558',\n           data: employeeDateData\n       }\n       ]\n     },\n"
                },
                {
                    "date": 1635951848393,
                    "content": "Index: \n===================================================================\n--- \n+++ \n@@ -40,9 +40,9 @@\n \n //Fetch Data from API\n \n async function getDummyData() {\n-  const apiUrl = \"https://json.extendsclass.com/bin/24cb4afca81e\";\n+  const apiUrl = \"restapi.json\";\n \n   const response = await fetch(apiUrl)\n   const barChatData = await response.json()\n   \n"
                },
                {
                    "date": 1635951857887,
                    "content": "Index: \n===================================================================\n--- \n+++ \n@@ -40,9 +40,9 @@\n \n //Fetch Data from API\n \n async function getDummyData() {\n-  const apiUrl = \"restapi.json\";\n+  const apiUrl = \"https://json.extendsclass.com/bin/24cb4afca81e\";\n \n   const response = await fetch(apiUrl)\n   const barChatData = await response.json()\n   \n"
                },
                {
                    "date": 1635953592253,
                    "content": "Index: \n===================================================================\n--- \n+++ \n@@ -40,9 +40,9 @@\n \n //Fetch Data from API\n \n async function getDummyData() {\n-  const apiUrl = \"https://json.extendsclass.com/bin/24cb4afca81e\";\n+  const apiUrl = \"https://json.extendsclass.com/bin/bb073434d9be\";\n \n   const response = await fetch(apiUrl)\n   const barChatData = await response.json()\n   \n"
                },
                {
                    "date": 1636013926582,
                    "content": "Index: \n===================================================================\n--- \n+++ \n@@ -40,17 +40,17 @@\n \n //Fetch Data from API\n \n async function getDummyData() {\n-  const apiUrl = \"https://json.extendsclass.com/bin/bb073434d9be\";\n+  const apiUrl = \"https://andrealeporialeide.github.io/invest.io/public/dummy-chart-main/restapi.json\";\n \n   const response = await fetch(apiUrl)\n   const barChatData = await response.json()\n   \n   const salary = barChatData.data.map((x) => x.employee_salary)\n   console.log(salary)\n   const Date = barChatData.data.map((x) => x.employee_Date)\n-  const name = barChatData.data.map((x) => x.employee_name)\n+  const name = barChatData.data.map((x) => x.employee_date)\n \n  employeeSalaryData = salary\n  employeeDateData = Date\n  employeeLabel = name\n"
                },
                {
                    "date": 1636014226781,
                    "content": "Index: \n===================================================================\n--- \n+++ \n@@ -0,0 +1,57 @@\n+var employeeLabel = [], employeeSalaryData = [], employeeDateData = []\n+\n+async function dummyChart() {\n+  await getDummyData()\n+\n+const ctx = document.getElementById('myChart').getContext('2d');\n+\n+const chart = new Chart(ctx, {\n+    // The type of chart we want to create\n+    type: 'line',\n+\n+    // The data for our dataset\n+    data: {\n+        labels: employeeLabel,\n+        datasets: [{\n+            label: 'Employee Salary',\n+            backgroundColor: '',\n+            borderColor: '#0A2558',\n+            data: employeeSalaryData\n+        },\n+        {\n+          label: 'Employee Date',\n+          backgroundColor: '',\n+          borderColor: '#0A2558',\n+          data: employeeDateData\n+      }\n+      ]\n+    },\n+\n+    // Configuration options go here\n+    options: {\n+      tooltips: {\n+        mode: 'index'\n+      }\n+    }\n+})}\n+\n+dummyChart()\n+\n+\n+//Fetch Data from API\n+\n+async function getDummyData() {\n+  const apiUrl = \"https://andrealeporialeide.github.io/invest.io/public/dummy-chart-main/restapi.json\";\n+\n+  const response = await fetch(apiUrl)\n+  const barChatData = await response.json()\n+  \n+  const salary = barChatData.data.map((x) => x.employee_salary)\n+  console.log(salary)\n+  const Date = barChatData.data.map((x) => x.employee_Date)\n+  const date = barChatData.data.map((x) => x.employee_date)\n+\n+ employeeSalaryData = salary\n+ employeeDateData = Date\n+ employeeLabel = date\n+}\n\\ No newline at end of file\n"
                },
                {
                    "date": 1636014253111,
                    "content": "Index: \n===================================================================\n--- \n+++ \n@@ -52,63 +52,6 @@\n   const date = barChatData.data.map((x) => x.employee_date)\n \n  employeeSalaryData = salary\n  employeeDateData = Date\n- employeeLabel = date\n-}\n-var employeeLabel = [], employeeSalaryData = [], employeeDateData = []\n-\n-async function dummyChart() {\n-  await getDummyData()\n-\n-const ctx = document.getElementById('myChart').getContext('2d');\n-\n-const chart = new Chart(ctx, {\n-    // The type of chart we want to create\n-    type: 'line',\n-\n-    // The data for our dataset\n-    data: {\n-        labels: employeeLabel,\n-        datasets: [{\n-            label: 'Employee Salary',\n-            backgroundColor: '',\n-            borderColor: '#0A2558',\n-            data: employeeSalaryData\n-        },\n-        {\n-          label: 'Employee Date',\n-          backgroundColor: '',\n-          borderColor: '#0A2558',\n-          data: employeeDateData\n-      }\n-      ]\n-    },\n-\n-    // Configuration options go here\n-    options: {\n-      tooltips: {\n-        mode: 'index'\n-      }\n-    }\n-})}\n-\n-dummyChart()\n-\n-\n-//Fetch Data from API\n-\n-async function getDummyData() {\n-  const apiUrl = \"https://andrealeporialeide.github.io/invest.io/public/dummy-chart-main/restapi.json\";\n-\n-  const response = await fetch(apiUrl)\n-  const barChatData = await response.json()\n-  \n-  const salary = barChatData.data.map((x) => x.employee_salary)\n-  console.log(salary)\n-  const Date = barChatData.data.map((x) => x.employee_Date)\n-  const name = barChatData.data.map((x) => x.employee_date)\n-\n- employeeSalaryData = salary\n- employeeDateData = Date\n- employeeLabel = name\n+ employedateLabel = date\n }\n\\ No newline at end of file\n"
                }
            ],
            "date": 1635949749529,
            "name": "Commit-0",
            "content": "var employeeLabel = [], employeeSalaryData = [], employeeDateData = []\n\nasync function dummyChart() {\n  await getDummyData()\n\nconst ctx = document.getElementById('myChart').getContext('2d');\n\nconst chart = new Chart(ctx, {\n    // The type of chart we want to create\n    type: 'bar',\n\n    // The data for our dataset\n    data: {\n        labels: employeeLabel,\n        datasets: [{\n            label: 'Employee Salary',\n            backgroundColor: 'blue',\n            borderColor: 'rgb(255, 99, 132)',\n            data: employeeSalaryData\n        },\n        {\n          label: 'Employee Date',\n          backgroundColor: 'pink',\n          borderColor: 'rgb(255, 99, 132)',\n          data: employeeDateData\n      }\n      ]\n    },\n\n    // Configuration options go here\n    options: {\n      tooltips: {\n        mode: 'index'\n      }\n    }\n})}\n\ndummyChart()\n\n\n//Fetch Data from API\n\nasync function getDummyData() {\n  const apiUrl = \"http://dummy.restapiexample.com/api/v1/employees\"\n\n  const response = await fetch(apiUrl)\n  const barChatData = await response.json()\n  \n  const salary = barChatData.data.map((x) => x.employee_salary)\n  console.log(salary)\n  const Date = barChatData.data.map((x) => x.employee_Date)\n  const name = barChatData.data.map((x) => x.employee_name)\n\n employeeSalaryData = salary\n employeeDateData = Date\n employeeLabel = name\n}"
        }
    ]
}